plotpen/__init__.py
plotpen/colors.py
plotpen/export.py
plotpen/markers.py
plotpen/scale.py
plotpen/svg.py
plotpen/tex.py
plotpen/ticks.py
plotpen/tikz.py
plotpen-0.0.4.dist-info/LICENSE
plotpen-0.0.4.dist-info/METADATA
plotpen-0.0.4.dist-info/WHEEL
plotpen-0.0.4.dist-info/top_level.txt
plotpen-0.0.4.dist-info/RECORD
