Metadata-Version: 2.1
Name: plotpen
Version: 0.0.4
Summary: SVG based plotting tools
Author: Thijs Vogels
License: Apache License
Project-URL: homepage, https://github.com/tvogels/plotpen
Project-URL: repository, https://github.com/tvogels/plotpen
Requires-Python: >=3.7
License-File: LICENSE
Requires-Dist: typing-extensions (>4)
Requires-Dist: flexbox (>=0.0.1)
Requires-Dist: domtree (>=0.0.5)
Requires-Dist: matplotlib
Provides-Extra: test
Requires-Dist: pytest ; extra == 'test'
